{"targets":[{"end":36,"type":"Situation Entity","begin":29},{"end":168,"type":"Situation Entity","begin":160},{"end":227,"type":"Situation Entity","begin":220},{"end":322,"type":"Situation Entity","begin":317},{"end":376,"type":"Situation Entity","begin":368},{"end":529,"type":"Situation Entity","begin":520},{"end":656,"type":"Situation Entity","begin":651},{"end":968,"type":"Situation Entity","begin":961},{"end":998,"type":"Situation Entity","begin":991},{"end":1208,"type":"Situation Entity","begin":1199},{"end":1365,"type":"Situation Entity","begin":1358},{"end":1555,"type":"Situation Entity","begin":1548},{"end":1648,"type":"Situation Entity","begin":1642},{"end":1800,"type":"Situation Entity","begin":1793},{"end":1882,"type":"Situation Entity","begin":1873},{"end":2114,"type":"Situation Entity","begin":2107},{"end":2215,"type":"Situation Entity","begin":2210},{"end":2256,"type":"Situation Entity","begin":2247},{"end":2397,"type":"Situation Entity","begin":2392},{"end":2819,"type":"Situation Entity","begin":2811},{"end":2985,"type":"Situation Entity","begin":2980},{"end":3017,"type":"Situation Entity","begin":3013},{"end":3076,"type":"Situation Entity","begin":3065},{"end":3237,"type":"Situation Entity","begin":3229},{"end":3340,"type":"Situation Entity","begin":3333},{"end":3368,"type":"Situation Entity","begin":3363},{"end":3724,"type":"Situation Entity","begin":3716},{"end":3857,"type":"Situation Entity","begin":3852},{"end":4198,"type":"Situation Entity","begin":4191},{"end":4452,"type":"Situation Entity","begin":4442},{"end":4734,"type":"Situation Entity","begin":4724},{"end":4938,"type":"Situation Entity","begin":4932},{"end":5031,"type":"Situation Entity","begin":5023},{"end":5265,"type":"Situation Entity","begin":5261},{"end":5314,"type":"Situation Entity","begin":5309},{"end":5550,"type":"Situation Entity","begin":5546},{"end":5651,"type":"Situation Entity","begin":5641},{"end":5732,"type":"Situation Entity","begin":5727},{"end":5817,"type":"Situation Entity","begin":5810},{"end":6112,"type":"Situation Entity","begin":6105},{"end":6142,"type":"Situation Entity","begin":6137},{"end":6259,"type":"Situation Entity","begin":6251},{"end":6327,"type":"Situation Entity","begin":6321},{"end":6378,"type":"Situation Entity","begin":6371},{"end":6519,"type":"Situation Entity","begin":6515},{"end":6646,"type":"Situation Entity","begin":6641},{"end":6846,"type":"Situation Entity","begin":6834},{"end":7152,"type":"Situation Entity","begin":7145},{"end":7440,"type":"Situation Entity","begin":7434},{"end":7550,"type":"Situation Entity","begin":7541},{"end":7641,"type":"Situation Entity","begin":7634},{"end":7701,"type":"Situation Entity","begin":7693},{"end":7774,"type":"Situation Entity","begin":7769},{"end":7956,"type":"Situation Entity","begin":7949},{"end":8115,"type":"Situation Entity","begin":8105},{"end":8270,"type":"Situation Entity","begin":8263},{"end":8330,"type":"Situation Entity","begin":8321},{"end":8524,"type":"Situation Entity","begin":8510},{"end":8563,"type":"Situation Entity","begin":8555},{"end":8647,"type":"Situation Entity","begin":8639},{"end":8748,"type":"Situation Entity","begin":8737},{"end":8865,"type":"Situation Entity","begin":8857},{"end":9040,"type":"Situation Entity","begin":9031},{"end":9208,"type":"Situation Entity","begin":9197},{"end":9329,"type":"Situation Entity","begin":9318},{"end":9391,"type":"Situation Entity","begin":9384},{"end":9500,"type":"Situation Entity","begin":9495},{"end":9745,"type":"Situation Entity","begin":9740},{"end":9828,"type":"Situation Entity","begin":9820},{"end":10062,"type":"Situation Entity","begin":10048},{"end":10106,"type":"Situation Entity","begin":10097},{"end":10331,"type":"Situation Entity","begin":10325},{"end":10413,"type":"Situation Entity","begin":10405},{"end":10456,"type":"Situation Entity","begin":10450},{"end":10492,"type":"Situation Entity","begin":10483},{"end":10597,"type":"Situation Entity","begin":10586},{"end":10684,"type":"Situation Entity","begin":10679},{"end":10768,"type":"Situation Entity","begin":10759},{"end":10827,"type":"Situation Entity","begin":10815},{"end":11160,"type":"Situation Entity","begin":11151},{"end":11310,"type":"Situation Entity","begin":11304},{"end":11650,"type":"Situation Entity","begin":11644},{"end":12039,"type":"Situation Entity","begin":12030},{"end":12114,"type":"Situation Entity","begin":12110},{"end":12231,"type":"Situation Entity","begin":12223},{"end":12327,"type":"Situation Entity","begin":12316},{"end":12463,"type":"Situation Entity","begin":12457},{"end":12562,"type":"Situation Entity","begin":12558},{"end":12747,"type":"Situation Entity","begin":12741},{"end":12847,"type":"Situation Entity","begin":12835},{"end":12893,"type":"Situation Entity","begin":12888},{"end":13028,"type":"Situation Entity","begin":13023},{"end":13482,"type":"Situation Entity","begin":13473},{"end":13600,"type":"Situation Entity","begin":13594},{"end":13689,"type":"Situation Entity","begin":13684},{"end":13917,"type":"Situation Entity","begin":13909},{"end":13977,"type":"Situation Entity","begin":13970},{"end":14047,"type":"Situation Entity","begin":14041},{"end":14246,"type":"Situation Entity","begin":14237},{"end":14312,"type":"Situation Entity","begin":14305},{"end":14565,"type":"Situation Entity","begin":14558},{"end":14945,"type":"Situation Entity","begin":14939},{"end":15014,"type":"Situation Entity","begin":15008},{"end":15132,"type":"Situation Entity","begin":15124},{"end":15335,"type":"Situation Entity","begin":15328},{"end":15525,"type":"Situation Entity","begin":15518},{"end":15878,"type":"Situation Entity","begin":15870},{"end":16034,"type":"Situation Entity","begin":16027},{"end":16294,"type":"Situation Entity","begin":16286},{"end":16359,"type":"Situation Entity","begin":16353},{"end":16473,"type":"Situation Entity","begin":16463},{"end":16505,"type":"Situation Entity","begin":16496},{"end":16645,"type":"Situation Entity","begin":16637},{"end":16742,"type":"Situation Entity","begin":16737},{"end":16877,"type":"Situation Entity","begin":16869},{"end":17095,"type":"Situation Entity","begin":17090},{"end":17229,"type":"Situation Entity","begin":17223},{"end":17305,"type":"Situation Entity","begin":17298},{"end":17562,"type":"Situation Entity","begin":17555},{"end":17729,"type":"Situation Entity","begin":17720},{"end":17836,"type":"Situation Entity","begin":17828},{"end":17954,"type":"Situation Entity","begin":17949},{"end":18113,"type":"Situation Entity","begin":18106},{"end":18220,"type":"Situation Entity","begin":18215},{"end":18422,"type":"Situation Entity","begin":18415},{"end":18513,"type":"Situation Entity","begin":18502},{"end":18913,"type":"Situation Entity","begin":18905},{"end":19043,"type":"Situation Entity","begin":19035},{"end":19193,"type":"Situation Entity","begin":19187},{"end":19330,"type":"Situation Entity","begin":19323},{"end":19404,"type":"Situation Entity","begin":19400},{"end":19522,"type":"Situation Entity","begin":19513},{"end":19671,"type":"Situation Entity","begin":19663},{"end":19756,"type":"Situation Entity","begin":19750},{"end":20012,"type":"Situation Entity","begin":20001},{"end":20267,"type":"Situation Entity","begin":20262},{"end":20398,"type":"Situation Entity","begin":20392},{"end":20447,"type":"Situation Entity","begin":20441},{"end":20648,"type":"Situation Entity","begin":20640},{"end":20791,"type":"Situation Entity","begin":20781},{"end":21071,"type":"Situation Entity","begin":21064},{"end":21118,"type":"Situation Entity","begin":21112},{"end":21245,"type":"Situation Entity","begin":21235},{"end":21300,"type":"Situation Entity","begin":21294},{"end":21359,"type":"Situation Entity","begin":21349},{"end":21587,"type":"Situation Entity","begin":21578},{"end":21612,"type":"Situation Entity","begin":21606},{"end":21736,"type":"Situation Entity","begin":21729},{"end":21776,"type":"Situation Entity","begin":21771},{"end":21804,"type":"Situation Entity","begin":21795},{"end":21954,"type":"Situation Entity","begin":21943},{"end":22081,"type":"Situation Entity","begin":22073},{"end":22190,"type":"Situation Entity","begin":22184},{"end":22259,"type":"Situation Entity","begin":22247},{"end":22348,"type":"Situation Entity","begin":22336},{"end":22381,"type":"Situation Entity","begin":22374},{"end":22721,"type":"Situation Entity","begin":22713},{"end":22786,"type":"Situation Entity","begin":22779},{"end":22917,"type":"Situation Entity","begin":22909},{"end":23007,"type":"Situation Entity","begin":23000},{"end":23140,"type":"Situation Entity","begin":23137},{"end":23462,"type":"Situation Entity","begin":23455},{"end":23614,"type":"Situation Entity","begin":23610},{"end":23719,"type":"Situation Entity","begin":23713},{"end":24002,"type":"Situation Entity","begin":23994},{"end":24065,"type":"Situation Entity","begin":24060},{"end":24125,"type":"Situation Entity","begin":24118},{"end":24255,"type":"Situation Entity","begin":24247},{"end":24400,"type":"Situation Entity","begin":24393},{"end":24571,"type":"Situation Entity","begin":24563},{"end":24587,"type":"Situation Entity","begin":24581},{"end":24640,"type":"Situation Entity","begin":24633},{"end":24691,"type":"Situation Entity","begin":24682},{"end":24824,"type":"Situation Entity","begin":24819},{"end":24865,"type":"Situation Entity","begin":24858},{"end":24987,"type":"Situation Entity","begin":24983},{"end":25093,"type":"Situation Entity","begin":25086},{"end":25139,"type":"Situation Entity","begin":25128},{"end":25262,"type":"Situation Entity","begin":25259},{"end":25378,"type":"Situation Entity","begin":25372},{"end":25486,"type":"Situation Entity","begin":25479},{"end":25564,"type":"Situation Entity","begin":25557},{"end":25682,"type":"Situation Entity","begin":25677},{"end":25797,"type":"Situation Entity","begin":25789},{"end":25873,"type":"Situation Entity","begin":25863},{"end":25963,"type":"Situation Entity","begin":25952},{"end":26220,"type":"Situation Entity","begin":26212},{"end":26252,"type":"Situation Entity","begin":26244},{"end":26445,"type":"Situation Entity","begin":26434},{"end":26617,"type":"Situation Entity","begin":26612},{"end":26744,"type":"Situation Entity","begin":26735},{"end":26862,"type":"Situation Entity","begin":26858},{"end":26968,"type":"Situation Entity","begin":26961},{"end":27046,"type":"Situation Entity","begin":27037},{"end":27234,"type":"Situation Entity","begin":27228},{"end":27391,"type":"Situation Entity","begin":27382},{"end":27553,"type":"Situation Entity","begin":27545},{"end":27627,"type":"Situation Entity","begin":27621},{"end":27835,"type":"Situation Entity","begin":27832},{"end":28143,"type":"Situation Entity","begin":28135},{"end":28231,"type":"Situation Entity","begin":28225}]}